pyquery_xpath/__init__.py
pyquery_xpath/pyquery_xpath.py
pyquery_xpath-0.6.dist-info/LICENSE.txt
pyquery_xpath-0.6.dist-info/METADATA
pyquery_xpath-0.6.dist-info/WHEEL
pyquery_xpath-0.6.dist-info/top_level.txt
pyquery_xpath-0.6.dist-info/RECORD
