Metadata-Version: 2.1
Name: pyquery-xpath
Version: 0.6
Summary: Adding XPath support to pyquery
Home-page: https://github.com/alleyfrost/pyquery_xpath
Author: alleyfrost
Author-email: alleyfrost@qq.com
License: GPLv3
Requires-Python: >=3.0
License-File: LICENSE.txt
Requires-Dist: pyquery
